texture_replicator/__init__.py
texture_replicator/replicator.py
texture_replicator/texture_replicator.py
texture_replicator-0.0.1.dist-info/LICENSE
texture_replicator-0.0.1.dist-info/METADATA
texture_replicator-0.0.1.dist-info/WHEEL
texture_replicator-0.0.1.dist-info/top_level.txt
texture_replicator-0.0.1.dist-info/RECORD
