Metadata-Version: 2.1
Name: texture-replicator
Version: 0.0.1
Summary: A package to replicate textures
Home-page: https://github.com/kwgiffor/texture-replicator
Author: Keegan Gifford
Author-email: keeganwp@gmail.com
License: UNKNOWN
Platform: UNKNOWN
Classifier: Programming Language :: Python :: 3.10
Classifier: License :: OSI Approved :: GNU General Public License v3 (GPLv3)
License-File: LICENSE
Requires-Dist: ipython (>=6)
Requires-Dist: nbformat (>=4)
Requires-Dist: nbconvert (>=5)
Requires-Dist: requests (>=2)
